baidubce/__init__.py
baidubce/bce_base_client.py
baidubce/bce_client_configuration.py
baidubce/bce_response.py
baidubce/compat.py
baidubce/exception.py
baidubce/protocol.py
baidubce/region.py
baidubce/utils.py
baidubce/auth/__init__.py
baidubce/auth/bce_credentials.py
baidubce/auth/bce_v1_signer.py
baidubce/http/__init__.py
baidubce/http/bce_http_client.py
baidubce/http/handler.py
baidubce/http/http_content_types.py
baidubce/http/http_headers.py
baidubce/http/http_methods.py
baidubce/retry/__init__.py
baidubce/retry/retry_policy.py
baidubce/services/__init__.py
baidubce/services/aihc/__init__.py
baidubce/services/aihc/aihc_client.py
baidubce/services/aihc/aihc_handler.py
baidubce/services/aihc/aihc_model.py
baidubce/services/aihc/base/__init__.py
baidubce/services/aihc/base/aihc_base_client.py
baidubce/services/aihc/base/aihc_common.py
baidubce/services/aihc/modules/__init__.py
baidubce/services/aihc/modules/dataset/__init__.py
baidubce/services/aihc/modules/dataset/dataset_client.py
baidubce/services/aihc/modules/dataset/dataset_model.py
baidubce/services/aihc/modules/dev_instance/__init__.py
baidubce/services/aihc/modules/dev_instance/dev_instance_client.py
baidubce/services/aihc/modules/job/__init__.py
baidubce/services/aihc/modules/job/job_client.py
baidubce/services/aihc/modules/job/job_model.py
baidubce/services/aihc/modules/model/__init__.py
baidubce/services/aihc/modules/model/model_client.py
baidubce/services/aihc/modules/model/model_model.py
baidubce/services/aihc/modules/resource_pool/__init__.py
baidubce/services/aihc/modules/resource_pool/resource_pool_client.py
baidubce/services/aihc/modules/service/__init__.py
baidubce/services/aihc/modules/service/service_client.py
baidubce/services/aihc/modules/service/service_model.py
baidubce/services/autoscaling/__init__.py
baidubce/services/autoscaling/as_client.py
baidubce/services/autoscaling/as_handler.py
baidubce/services/autoscaling/as_model.py
baidubce/services/bbc/__init__.py
bce_python_sdk-0.9.57.dist-info/METADATA
bce_python_sdk-0.9.57.dist-info/WHEEL
bce_python_sdk-0.9.57.dist-info/top_level.txt
bce_python_sdk-0.9.57.dist-info/RECORD
