Metadata-Version: 2.4
Name: bce-python-sdk
Version: 0.9.57
Summary: BCE SDK for python
Home-page: http://bce.baidu.com
Author: 
Author-email: 
License: Apache License 2.0
Requires-Python: >=2.7, !=3.0.*, !=3.1.*, !=3.2.*, <4
Requires-Dist: pycryptodome>=3.8.0
Requires-Dist: future>=0.6.0
Requires-Dist: six>=1.4.0
Dynamic: home-page
Dynamic: license
Dynamic: requires-dist
Dynamic: requires-python
Dynamic: summary
